fling_core/__init__.py
fling_core/fling.yaml
fling_core/github.py
fling_core-0.1.2.dist-info/METADATA
fling_core-0.1.2.dist-info/WHEEL
fling_core-0.1.2.dist-info/RECORD
